CHANGELOG.md
LICENSE
MANIFEST.in
README.md
requirements.txt
setup.py
pixelpin_auth_sqlalchemy/__init__.py
pixelpin_auth_sqlalchemy/storage.py
pixelpin_auth_storage_sqlalchemy.egg-info/PKG-INFO
pixelpin_auth_storage_sqlalchemy.egg-info/SOURCES.txt
pixelpin_auth_storage_sqlalchemy.egg-info/dependency_links.txt
pixelpin_auth_storage_sqlalchemy.egg-info/not-zip-safe
pixelpin_auth_storage_sqlalchemy.egg-info/requires.txt
pixelpin_auth_storage_sqlalchemy.egg-info/top_level.txt