Metadata-Version: 1.1
Name: pixelpin-auth-storage-sqlalchemy
Version: 1.0.0
Summary: Python Social Authentication, SQLAlchemy storage.
Home-page: https://github.com/python-social-auth/social-storage-sqlalchemy
Author: ['Matias Aguirre', 'Callum Brankin']
Author-email: callum@pixelpin.co.uk
License: BSD
Keywords: sqlalchemy,social auth,pixelpin auth
Platform: UNKNOWN
Classifier: Development Status :: 4 - Beta
Classifier: Topic :: Internet
Classifier: License :: OSI Approved :: BSD License
Classifier: Intended Audience :: Developers
Classifier: Environment :: Web Environment
Classifier: Programming Language :: Python
Classifier: Programming Language :: Python :: 2.7
Classifier: Programming Language :: Python :: 3
